miou/evaluate.py
miou-0.0.0.dist-info/licenses/LICENSE
miou-0.0.0.dist-info/METADATA
miou-0.0.0.dist-info/WHEEL
miou-0.0.0.dist-info/top_level.txt
miou-0.0.0.dist-info/RECORD
