Metadata-Version: 2.4
Name: miou
Version: 0.0.0
Summary: miou
Author-email: Dan Jacobellis <danjacobellis@utexas.edu>
License-Expression: LicenseRef-Proprietary
Classifier: Programming Language :: Python :: 3
Classifier: Operating System :: OS Independent
Requires-Python: >=3.6
License-File: LICENSE
Requires-Dist: torch
Requires-Dist: torchvision
Requires-Dist: torchmetrics
Requires-Dist: pillow
Dynamic: license-file
